{
  "Hangzhou": {
    "tagline": "中国数字经济之都、全球视频监控中枢——阿里巴巴/蚂蚁、海康威视与大华（全球第一、第二大安防摄像头厂商），并发展 RISC-V 芯片设计（平头哥）与工业物联网。",
    "clusters": [
      {"seg": "视频监控与视觉 AI", "what": "海康威视与大华——全球第一、第二大安防摄像头厂商；图像传感器与边缘 AI SoC 用量极大。"},
      {"seg": "互联网、云与数字经济", "what": "阿里巴巴与蚂蚁总部 + 网易——中国电商、云与金融科技核心。"},
      {"seg": "芯片设计（RISC-V / SoC）", "what": "阿里平头哥——倚天服务器 CPU 与 RISC-V（玄铁）；并自研视觉 SoC。"},
      {"seg": "工业物联网与自动化", "what": "流程自动化与智能制造基地（滨江）。"}
    ],
    "subdistricts": [
      {"focus": "海康威视、大华、安防/物联网、芯片设计"},
      {"focus": "阿里巴巴、云、AI、电商（余杭）"}
    ],
    "valuechain": "净消费与集成方——安防、服务器与物联网拉动图像传感器、边缘 AI SoC、内存与网络；以软件/互联网为主导，自研芯片设计快速增长。",
    "sourcing": {"buy": ["CMOS 图像传感器", "边缘 AI / 视觉 SoC", "内存与存储", "网络与电源器件"], "sell": ["安防系统与摄像头", "云与电商平台", "物联网/工业设备"]},
    "stats": [{"k": "2024 GDP", "v": "约 ¥2.18 万亿"}, {"k": "海康 / 大华", "v": "全球第 1、2 大安防"}, {"k": "阿里 / 蚂蚁", "v": "全球总部"}],
    "note": "以互联网/安防/物联网为主导——芯片消费大户、设计快速成长，而非晶圆制造基地。海康威视与大华在美国实体清单。"
  },
  "Ningbo": {
    "tagline": "并非芯片之城，而是元件、特殊材料与汽车电子 Tier-1 重镇；民营主导，依托全球第一大货运港。",
    "clusters": [
      {"seg": "稀土 NdFeB 磁体", "what": "中国”磁都”——占全国产量 40% 以上；用于新能源车/风电/机器人电机。地缘政治敏感（2025 年稀土出口管制）。"},
      {"seg": "汽车电子 / Tier-1 零部件", "what": "中国最密集的民营 Tier-1 集群；50 公里范围内约 5,000 家汽车零部件企业；4 家跻身全球前 100。"},
      {"seg": "电池材料", "what": "人造石墨负极与高镍正极全球第一。"},
      {"seg": "精密光学", "what": "全球每 3 块 Android 摄像头模组中有 1 块产自此地；车载镜头全国第一。"},
      {"seg": "继电器 / 连接器 / 低压电器", "what": "继电器年产 2 亿只以上；观海卫是全球最大欧式插座生产基地。"},
      {"seg": "小家电", "what": "慈溪生产全球约 60% 的小家电（电熨斗 60%，吹风机 30%）。"},
      {"seg": "模具 / 塑料 + 注塑机", "what": "余姚为中国”塑料之都”/模具之都；注塑机产量全球第一。"},
      {"seg": "逆变器 / 储能 + 光伏", "what": "主要逆变器/储能出口商；HJT 太阳能。"},
      {"seg": "半导体材料 / OSAT", "what": "溅射靶材全球第一；OSAT 全球第 14（余姚）。"}
    ],
    "subdistricts": [
      {"focus": "小家电 + 插座/连接器 + 轴承；磁体"},
      {"focus": "塑料之都 + 模具之都；Sunny Optical；半导体靶材"},
      {"focus": "深水港；汽车零部件园区；磁体；钢铁"},
      {"focus": "总部集聚区——Yunsheng 韵升、Shanshan 杉杉、Ronbay 容百；汽车 Tier-1"},
      {"focus": "中国石化镇海炼化——全国最大炼厂（塑料/薄膜原料）"},
      {"focus": "光学薄膜集群；传感器"}
    ],
    "valuechain": "处于元件 / 特殊材料 / Tier-1 子系统层——非芯片、非整机组装、非设计。民营企业基因（民企占市场主体 96.7%，提供 85% 就业）；出口与港口驱动。",
    "sourcing": {
      "buy": [
        "继电器、连接器、低压电器",
        "NdFeB 磁体及组件",
        "精密塑料外壳 / 模具",
        "摄像头模组及光学薄膜",
        "电池负极/正极材料"
      ],
      "sell": [
        "汽车 MCU / 功率半导体 / SiC-GaN（供 Joyson 均胜、Tuopu 拓普）",
        "汽车线束用连接器",
        "特种石墨/硅材料（供 Shanshan 杉杉）",
        "测试与测量设备"
      ]
    },
    "stats": [
      {"k": "2024 贸易", "v": "¥1.42 万亿（全国第 5）"},
      {"k": "制造业单项冠军", "v": "104 家以上（全国第 1）"},
      {"k": "港口", "v": "货运第 1 / 集装箱第 3"}
    ],
    "note": "AI 深度研究，交叉核验（已排查常见错误：德力西属温州，华帝属广东，福耀属福建——均非宁波）。"
  },
  "Guangzhou": {
    "tagline": "中国汽车制造之都 + 贸易门户（广交会）+ ”世界显示之都”；以国企/合资和整车组装为主，与深圳的民营设计生态截然相反。",
    "clusters": [
      {"seg": "汽车与新能源车", "what": "全国顶级汽车产出城市——2024 年约 318 万辆（38% 为新能源），涵盖 ICE+混动+BEV 六大整车品牌；南沙成为重要的汽车出口枢纽。"},
      {"seg": "显示面板 / 超高清", "what": "”世界显示之都”——TCL CSOT T9 8.6 代线（月产 18 万片，年产值约 ¥300 亿）+ 接手 LG Display 广州 LCD 工厂。全球电视面板第 2。"},
      {"seg": "汽车零部件 / 汽车电子", "what": "花都、番禺深度 Tier-1/Tier-2 供应商集群，为本地整车及出口配套。"},
      {"seg": "生物医药 / 制药", "what": "重要生物医药集群——生物岛，4,000 家以上企业，营收 ¥2,100 亿。"},
      {"seg": "石油化工", "what": "珠江口炼化（规模小于茂名/湛江）。"},
      {"seg": "半导体（成熟制程）", "what": "广州唯一具备规模的晶圆厂——特种模拟/功率/显示驱动（180–55nm）；2025 年营收 +53% 至 ¥25.8 亿，但深度亏损，拟科创板上市。"}
    ],
    "subdistricts": [
      {"focus": "旗舰先进制造区——占广州工业产值约 40%；CanSemi 晶圆厂、广汽本田新能源工厂、生物医药"},
      {"focus": "港口/自贸区（2,050 万 TEU，全球前十）；广汽丰田；石化；汽车出口 +68%"},
      {"focus": "广汽埃安 EV 工厂及研发；小鹏（含昊铂飞行汽车试验工厂）"},
      {"focus": "东风日产工厂 + 广州汽车零部件城"},
      {"focus": "精密金属冲压 / 连接器端子制造"},
      {"focus": "小鹏 HQ 园区 + 企业/科技服务"}
    ],
    "valuechain": "整车组装 + 贸易门户 + 重工业层——芯片、传感器、功率器件和面板的净消费者（组装入整车），并非元件原产地。国企/合资主导程度高于私营的深圳（广汽、中石化、中海油、广药）。广交会 = 中国最大 B2B 出口撮合平台。",
    "sourcing": {
      "buy": [
        "CanSemi 成熟制程晶圆（180–55nm 模拟/功率/显示驱动）",
        "连接器端子 / 精密冲压件（增城）",
        "显示生态配套（OCA / FPC / 背光）"
      ],
      "sell": [
        "汽车半导体——MCU / 功率 / ADAS / CAN-LIN，供广汽 200 万辆以上",
        "新能源功率器件——SiC / IGBT / 栅极驱动，供埃安和小鹏",
        "显示驱动 IC + PMIC，供 CSOT T9",
        "BMS 及 AI 计算 SoC / 激光雷达驱动，供小鹏智能电动车"
      ]
    },
    "stats": [
      {"k": "GDP 2024", "v": "¥3.1 万亿（全国第 4）"},
      {"k": "汽车产量 2024", "v": "约 318 万辆（38% 为新能源）"},
      {"k": "南沙港", "v": "2,050 万 TEU（全球前十）"}
    ],
    "note": "AI 深度研究（Sonnet），交叉核验——已标注：小鹏生产分布于广州+肇庆；东风日产母公司总部在武汉；原规划南沙乙烯裂解项目已迁至湛江。"
  },
  "Shanghai": {
    "tagline": "中国唯一具备完整垂直一体化半导体产业链的城市——晶圆代工、先进 IC 设计、材料与设备——以张江的 SMIC 和华虹为核心锚点；同时拥有 Tesla 超级工厂。",
    "clusters": [
      {"seg": "晶圆代工", "what": "SMIC（总部；2024 年营收创历史新高 ¥578 亿，+27.7%，全球代工份额约 5.5%）+ 华虹；临港新建合资晶圆厂。"},
      {"seg": "IC 设计", "what": "全国 IC 设计第一城——2024 年 ¥1,795 亿（约占全国 ¥6,689 亿的 27%）；张江设计企业数以百计。"},
      {"seg": "半导体设备与材料", "what": "张江及临港自贸区本土设备/材料企业持续壮大。"},
      {"seg": "汽车 / 新能源车", "what": "Tesla 上海超级工厂年产约 95 万辆（2024 年 11 月交付第 300 万辆）；SAIC、NIO。"}
    ],
    "subdistricts": [
      {"focus": "IC 设计 + SMIC/华虹晶圆厂（”中国硅谷”）"},
      {"focus": "SMIC 合资新厂 + Tesla 超级工厂；自贸区半导体激励政策"},
      {"focus": "华虹 8 英寸晶圆厂，电子 EMS"}
    ],
    "valuechain": "设计 → 代工 → 封装，成熟制程领域全国领先（14–28nm）；代工层为国企/国资背景（SMIC），设计和 EMS 层以私营及外资为主。",
    "sourcing": {
      "buy": [
        "成熟制程逻辑 IC（28–90nm）、MCU、功率及模拟芯片",
        "8 英寸晶圆",
        "国产 EDA 授权"
      ],
      "sell": [
        "半导体设备",
        "先进封装材料",
        "OSAT 服务",
        "PCB 基板"
      ]
    },
    "stats": [
      {"k": "SMIC 2024", "v": "¥578 亿（+27.7%）"},
      {"k": "IC 设计 2024", "v": "¥1,795 亿（全国第 1）"},
      {"k": "GDP 2024", "v": ">¥5 万亿"}
    ],
    "note": "Tesla 总部美国，Foxconn 总部台湾；华虹最先进的 12 英寸产线在无锡，非上海。"
  },
  "Shenzhen": {
    "tagline": "中国的硬件硅谷——无晶圆厂芯片设计（HiSilicon）、整机电子（DJI）、垂直一体化新能源车（BYD）与华强北元件市场共存；东莞组装深圳设计的产品。",
    "clusters": [
      {"seg": "无晶圆厂 IC / AI 芯片设计", "what": "HiSilicon 设计麒麟 SoC 和昇腾 AI 加速器；国家高新技术企业超 25,000 家（12 家/平方公里）。"},
      {"seg": "智能终端 / 消费电子", "what": "Foxconn 龙华代工 iPhone（约 30 万员工）；DJI 占全球消费级无人机市场 70% 以上。"},
      {"seg": "新能源车及产业链", "what": "BYD 2024 年 11 月交付第 1,000 万辆新能源车；深圳占中国新能源车产量 22.3%；本地自产电芯 + IGBT。"},
      {"seg": "软件 / 互联网 / 云计算", "what": "腾讯；战略性新兴产业占 GDP 42.3%；研发投入占 GDP 6.46%（全国第 1）。"},
      {"seg": "元件现货市场", "what": "华强北——全球最大电子元件市场；可实现当日 BOM 备货。"}
    ],
    "subdistricts": [
      {"focus": "腾讯、DJI、华为总部；高新园区；风险投资集群"},
      {"focus": "Foxconn iPhone 整机组装"},
      {"focus": "BYD 汽车/新能源车 + IGBT 功率半导体"},
      {"focus": "华强北元件市场；金融"},
      {"focus": "半导体设备、先进材料、光伏"}
    ],
    "valuechain": "珠三角产业链的设计 + 品牌 + 整合顶端；绝大多数为民营（华为/BYD/DJI/腾讯）；净出口 IP 密集的成品。",
    "sourcing": {
      "buy": [
        "裸芯片（经台湾 TSMC 供应）",
        "精密模具（东莞）",
        "电芯",
        "PCB",
        "稀土磁体"
      ],
      "sell": [
        "智能手机、无人机、新能源车、5G 基站、AI 服务器、IoT——经 ¥4.5 万亿出口（全国第 1）"
      ]
    },
    "stats": [
      {"k": "GDP 2024", "v": "¥3.68 万亿（+5.8%）"},
      {"k": "出口 2024", "v": "¥4.5 万亿（全国第 1）"},
      {"k": "新能源车份额", "v": "占全国 22.3%"}
    ],
    "note": "Foxconn 总部台湾（深圳为其最大运营基地）；HiSilicon 为华为子公司。"
  },
  "Beijing": {
    "tagline": "中国半导体研发 + 设备之都（非量产晶圆城）——Naura（国内设备第 1）、SMIC 北京晶圆厂、中关村 IC 设计集群、BOE 总部，以及全国最大自动驾驶开放测试区。",
    "clusters": [
      {"seg": "半导体设备", "what": "Naura——2024 年全球设备排名第 6，营收 ¥298 亿（+35%）；占中国刻蚀/沉积前道设备约 25%。"},
      {"seg": "IC 设计（无晶圆厂）", "what": "海淀 IC 营收 ¥430 亿（2024 年，+13%）；GigaDevice 为全球第 2 大 SPI NOR Flash；Cambricon 生产 AI NPU。"},
      {"seg": "晶圆制造", "what": "SMIC 北京 FAB4（亦庄）——成熟制程 ≥28nm，是 SMIC 月产能 120 万片以上网络的组成部分。"},
      {"seg": "显示", "what": "BOE 全球总部（以管理/研发为主；先进 OLED 生产线在成都/武汉）。"},
      {"seg": "自动驾驶 / AI", "what": "亦庄——百度 Apollo Go + 中国首批无人驾驶 Robotaxi 许可证（累计超 1,700 万次出行）。"}
    ],
    "subdistricts": [
      {"focus": "IC 设计、EDA、AI、大学科研院所（清华、北大、中科院）孵化"},
      {"focus": "Naura、SMIC 北京晶圆厂、BOE 产线、百度 Apollo Park"}
    ],
    "valuechain": "上游研发 + 设备层——私营无晶圆厂（GigaDevice、Cambricon）+ 国资设备（Naura）和代工（SMIC）；国家集成电路大基金支持。",
    "sourcing": {
      "buy": [
        "硅片、特种气体、光掩模、封装基板"
      ],
      "sell": [
        "晶圆制造设备（国内销售 + 出口）",
        "NOR Flash 芯片",
        "AI / 端侧 NPU",
        "显示面板（经 BOE 总部）",
        "Robotaxi 出行服务"
      ]
    },
    "stats": [
      {"k": "Naura 2024", "v": "¥298 亿（全球设备第 6）"},
      {"k": "海淀 IC", "v": "¥430 亿（+13%）"},
      {"k": "GigaDevice", "v": "NOR Flash 全球第 2"}
    ],
    "note": "华虹在北京无晶圆厂（全部在上海）。BOE 最先进 OLED 产线在成都/武汉，非北京。"
  },
  "Tianjin": {
    "tagline": "华北港口工业基地——汽车（FAW-Toyota）、空客 A320 总装、石油化工及新兴新能源车/电子，依托天津港及滨海新区。",
    "clusters": [
      {"seg": "汽车", "what": "FAW-Toyota + FAW 历史积累；北方汽车带新能源整车组装持续扩张。"},
      {"seg": "航空航天", "what": "空客 A320 总装线——欧洲以外首条；航空及运载火箭工厂。"},
      {"seg": "石油化工", "what": "大型炼化及化工基地（南港石化区）。"},
      {"seg": "电子 / 新能源车零部件", "what": "滨海/泰达显示、新能源车电池/零部件及电子（三星规模已压缩）。"}
    ],
    "subdistricts": [
      {"focus": "港口、石化、航空航天、电子"},
      {"focus": "汽车、电子、外资制造"}
    ],
    "valuechain": "重工业 + 整车组装 + 港口物流；国企主导（FAW、中石化、中石油），汽车/航空航天引入外资。",
    "sourcing": {
      "buy": [
        "汽车零部件",
        "石化原料",
        "电子元器件"
      ],
      "sell": [
        "汽车半导体 / 新能源车功率器件",
        "工业电子"
      ]
    },
    "stats": [
      {"k": "定位", "v": "汽车 + 空客 A320 总装线 + 港口"},
      {"k": "GDP", "v": "约 ¥1.8 万亿"}
    ],
    "note": "内容较精简（非深度研究城市）——天津以重工业/港口为主，非电子主导；如需深入分析，请标记跟进。"
  },
  "Suzhou": {
    "tagline": "中国外资驱动的电子及先进元件带首位城市（”苏南模式”）——Samsung、Bosch、ZEISS + 数千家台资企业，覆盖 PCB、OSAT、精密元件与生物医药。",
    "clusters": [
      {"seg": "外资电子及 EMS", "what": "苏州工业园 GDP ¥4,000 亿（2024）；全市工业产值 >¥4.7 万亿；高新技术产值占比 54.7%。"},
      {"seg": "半导体封装 / OSAT", "what": "重要 OSAT 集群——Samsung 苏州 DRAM 封装 + 台资 OSAT。"},
      {"seg": "PCB 及电子材料", "what": "昆山台资 PCB 厂商；东山精密（国内顶尖 PCB/精密集团）。"},
      {"seg": "光学 / 精密仪器", "what": "ZEISS 研发+制造基地（2024 年）；Sodick 精密电火花机。"},
      {"seg": "生物医药", "what": "生物纳米园（BioBAY）——中国领先生物医药集群，1,200 余家企业。"}
    ],
    "subdistricts": [
      {"focus": "半导体、生物科技、研发——GDP ¥4,000 亿（2024）"},
      {"focus": "台资 PCB/EMS/服务器（AI 服务器 2027 年目标 ¥1,000 亿）"},
      {"focus": "东山精密；汽车电子供应商"}
    ],
    "valuechain": "外资及台湾资本位于中高端电子层；后道半导体及半成品组装实力强；国企角色有限（”苏南模式”）。",
    "sourcing": {
      "buy": [
        "DRAM 封装",
        "SMT/EMS 半成品组装",
        "硬板及柔性 PCB",
        "精密机加工件",
        "光学镀膜"
      ],
      "sell": [
        "半导体资本设备",
        "ABF/BT 基板",
        "洁净室耗材",
        "自动化系统"
      ]
    },
    "stats": [
      {"k": "GDP 2024", "v": "¥26,720 亿（+6%）"},
      {"k": "高新技术产值", "v": "¥25,720 亿（54.7%）"},
      {"k": "苏州工业园 GDP", "v": "¥4,000 亿"}
    ],
    "note": "Samsung（韩）、ZEISS（德）、Foxconn（台）、ASE（台）、Unimicron（台）均为外资/台资总部。"
  },
  "Wuxi": {
    "tagline": "全国 IC 封装测试第 1 基地 + 华虹最新 12 英寸特色晶圆厂 + SK hynix DRAM 晶圆厂 + 全国唯一国家级 IoT 先进制造业集群。",
    "clusters": [
      {"seg": "IC 封装测试（OSAT）", "what": "全国第 1；高新区 IC 产值 >¥1,700 亿（2024）；500 余家 IC 企业。"},
      {"seg": "晶圆代工（12 英寸特色）", "what": "华虹无锡二期（40nm MCU/eNVM），目标月产能 83,000 片；STMicro 40nm eNVM 工艺转移。"},
      {"seg": "DRAM / 存储", "what": "SK hynix 无锡 DRAM 月产能约 18–19 万片，约 90% 为 1a 代 DDR5；49.9% 股权 2024 年出售给无锡国资。"},
      {"seg": "IoT / 传感器", "what": "中国唯一国家级 IoT 先进制造业集群；IoT 企业 3,000 余家；¥4,010 亿（2022 年）。"}
    ],
    "subdistricts": [
      {"focus": "IC 代工 + 封装 + IoT；500 余家 IC 企业"}
    ],
    "valuechain": "全栈半导体：设计（轻度）→ 代工 → OSAT → IoT 应用层；代工和 IoT 有国资引导，封装龙头长电为大型民营企业。",
    "sourcing": {
      "buy": [
        "封装成品 / OSAT 服务",
        "12 英寸特色晶圆（MCU/功率/NVM）",
        "DRAM 模组",
        "IoT 传感器模组"
      ],
      "sell": [
        "封装设备与材料（打线、倒装、WLP）",
        "精密引线框架",
        "IoT 通信模组"
      ]
    },
    "stats": [
      {"k": "高新区 IC 产值", "v": ">¥1,700 亿（三年全国第 2）"},
      {"k": "SK hynix 无锡", "v": "月产能约 18–19 万片"},
      {"k": "IoT（2022）", "v": "¥4,010 亿"}
    ],
    "note": "华虹总部上海（无锡为最大生产基地）；SK hynix 总部韩国（部分股权已归中国国资）。"
  },
  "Hefei": {
    "tagline": "中国最大胆的”政府即风险投资”城市——合肥市政府押注 BOE（显示）、CXMT（DRAM）和 NIO/大众（新能源车），成为存储、大尺寸面板和高端新能源车的三重领军。",
    "clusters": [
      {"seg": "DRAM / 存储", "what": "CXMT——中国唯一量产 DRAM 厂商；月产能约 16 万片；全球份额约 7.7%；DDR5 爬坡中（良率约 80%）。"},
      {"seg": "大尺寸面板", "what": "BOE（2008 年起合肥国资入股）——LCD G8.5 代 + WOLED。"},
      {"seg": "新能源车 / 汽车", "what": "NIO（合肥合资）+ 大众安徽（€25 亿）；2024 年新能源车约 137 万辆（占全国 8.3%）。"},
      {"seg": "家电", "what": "美的 / 格力合肥工厂。"}
    ],
    "subdistricts": [
      {"focus": "BOE + CXMT 晶圆厂，半导体集群"},
      {"focus": "NIO 新能源车制造 + 供应链园区"},
      {"focus": "大众安徽；家电"}
    ],
    "valuechain": "每家龙头企业均有国资介入（合肥政府持有 CXMT、NIO、BOE、大众安徽股权）——全国干预程度最深的市级模式；运营主体为上市/民营/合资企业。",
    "sourcing": {
      "buy": [
        "DRAM（DDR4/5、LPDDR5X）",
        "大尺寸 LCD/OLED 面板",
        "新能源车电池包及动力总成"
      ],
      "sell": [
        "DRAM 及面板制造设备",
        "新能源车制造自动化",
        "半导体材料"
      ]
    },
    "stats": [
      {"k": "GDP 2024", "v": "¥13,500 亿（+6.1%）"},
      {"k": "新能源车 2024", "v": "137 万辆（占全国 8.3%）"},
      {"k": "CXMT", "v": "全球 DRAM 份额约 7.7%"}
    ],
    "note": "NIO 总部上海；BOE 总部北京；大众总部德国——合肥为制造基地兼重要国资股东。"
  },
  "Wuhan": {
    "tagline": "中国唯一存储芯片与光电子一体化枢纽——YMTC 3D NAND 支撑全球密度最高的光纤/光电子集群（”光谷”）。",
    "clusters": [
      {"seg": "3D NAND 闪存", "what": "YMTC 月产能约 13 万片（三期后目标 20 万片以上）；目标 2026 年全球 NAND 份额约 15%。"},
      {"seg": "光纤及光缆", "what": "光谷占全球光纤预制棒产量约 40%；YOFC 为全球第 3 大光纤厂商。"},
      {"seg": "显示 LCD / OLED", "what": "BOE + TCL CSOT 产线；CSOT t8 G8.6 喷墨打印 OLED（全球首条）。"},
      {"seg": "光电子与激光器", "what": "企业逾 15,000 家；产业规模 ¥6,000 亿（2024）；光纤激光、激光雷达、光子芯片。"}
    ],
    "subdistricts": [
      {"focus": "光纤、YMTC、显示、激光——产值 >¥1.2 万亿"},
      {"focus": "汽车及新能源车整车组装"}
    ],
    "valuechain": "存储上中游（YMTC 全栈 NAND）+ 光子（预制棒 → 光缆 → 器件）；国资主导，后制裁时代外资有限。",
    "sourcing": {
      "buy": [
        "NAND 闪存（YMTC）",
        "光纤及光缆",
        "光电子模组",
        "显示面板"
      ],
      "sell": [
        "存储芯片供 OEM 品牌",
        "光纤供电信运营商",
        "面板供电视/汽车品牌"
      ]
    },
    "stats": [
      {"k": "YMTC", "v": "月产能约 13 万片（目标 20 万片以上）"},
      {"k": "光纤预制棒", "v": "占全球约 40%"},
      {"k": "光电子产业", "v": "¥6,000 亿（2024）"}
    ],
    "note": "YMTC 自 2022 年起列入美国实体清单；BOE/CSOT 为分支产线（总部分别在北京/深圳）；YMTC 产能为分析师估算。"
  },
  "Xi'an": {
    "tagline": "中国唯一将 Samsung 最大境外 NAND 基地（约占 Samsung NAND 产量 40%）、LONGi 全球领先太阳能园区与深厚航空航天/国防电子基地集于一体的城市。",
    "clusters": [
      {"seg": "NAND 闪存", "what": "Samsung 西安（X1+X2）= Samsung 全球 NAND 约 40%；正在由 236 层升级至 286 层 V9。"},
      {"seg": "太阳能硅片与电池", "what": "LONGi 总部——¥452 亿扩产计划，目标硅片 100GW + 电池 50GW 产能。"},
      {"seg": "航空航天及国防电子", "what": "西飞（AVIC 西安飞机）；抗辐照 IC 用于航天。"},
      {"seg": "半导体封装", "what": "Micron 后端封装（2023 年网络安全审查后状态不明）。"}
    ],
    "subdistricts": [
      {"focus": "LONGi 总部 + 制造基地"},
      {"focus": "Samsung 晶圆厂综合体，IC 设计"},
      {"focus": "AVIC、航天科工国防电子"}
    ],
    "valuechain": "双轨并行：Samsung 代工 = 外资出口型；LONGi = 民营全球冠军；国防/航空航天 = 国企封闭供应链。",
    "sourcing": {
      "buy": [
        "NAND 闪存（Samsung）",
        "太阳能硅片/电池（LONGi）",
        "航电/雷达",
        "航天级 IC"
      ],
      "sell": [
        "NAND 供全球存储 OEM",
        "太阳能硅片/电池供组件厂商"
      ]
    },
    "stats": [
      {"k": "Samsung 西安", "v": "约占 Samsung NAND 40%"},
      {"k": "LONGi 扩产", "v": "¥452 亿"},
      {"k": "LONGi 目标", "v": "100GW 硅片"}
    ],
    "note": "Samsung 总部韩国（持有美国出口豁免）；LONGi 光伏定义西安，尽管其并非传统半导体。"
  },
  "Chengdu": {
    "tagline": "中国西部 EMS + 封装节点——Foxconn 组装 MacBook/iPad，Intel 在此推进中国芯片封装扩产；IC 设计方兴未艾，同时是顶级游戏研发中心。",
    "clusters": [
      {"seg": "EMS——消费电子", "what": "Foxconn（2010 年起代工 iPad、MacBook、Apple Watch）；产品附加值较高。"},
      {"seg": "半导体封装测试", "what": "Intel 成都 +3 亿美元扩产（服务器芯片封装）+ 客户技术中心。"},
      {"seg": "IC 设计", "what": "中国”IC 第四城”；AMEC 设备基地规模 ¥30.5 亿；天府新区汽车芯片集群。"},
      {"seg": "游戏与软件", "what": "上海/深圳之后的最大游戏中心（腾讯/网易/米哈游）——推动 GPU/数据中心需求。"}
    ],
    "subdistricts": [
      {"focus": "Intel、Foxconn、IC 设计、AMEC"},
      {"focus": "IC 设计初创企业，汽车芯片"}
    ],
    "valuechain": "中下游：整机组装（Foxconn）为最大体量；Intel 封装增添后道深度；IC 设计处于早期阶段；外资制造主导 + 私营 IC/游戏。",
    "sourcing": {
      "buy": [
        "OSAT/封装（Intel）",
        "消费电子组装（Foxconn）",
        "IC 设计",
        "半导体设备（AMEC）"
      ],
      "sell": [
        "平板/笔记本/MacBook",
        "封装服务器芯片"
      ]
    },
    "stats": [
      {"k": "Intel 成都", "v": "+3 亿美元（服务器封装）"},
      {"k": "Foxconn", "v": "iPad / MacBook 生产基地"},
      {"k": "AMEC 规模", "v": "¥30.5 亿"}
    ],
    "note": "Foxconn（台）、Intel（美）、Pegatron（台）均为分支运营；未发现联电（UMC）成都晶圆厂的确认信息。"
  },
  "Chongqing": {
    "tagline": "全球最大笔记本电脑生产城市（占全球笔记本约 30%，连续 11 年第一），正在其 EMS 基础上叠加新能源汽车电子和显示产业。",
    "clusters": [
      {"seg": "笔记本 / 电脑 EMS", "what": "年产笔记本约 8,000 万台 + 智能终端逾 1 亿台；占全球笔记本约 30%；供 HP/Dell/Lenovo/Acer/Asus。"},
      {"seg": "新能源车及汽车电子", "what": "2024 年汽车产量 254 万辆，新能源车 95.3 万辆（+90.5%）；全国第 3。"},
      {"seg": "半导体封装", "what": "SK hynix 重庆后端封装工厂。"},
      {"seg": "显示", "what": "BOE 产线；成渝显示走廊的组成部分。"}
    ],
    "subdistricts": [
      {"focus": "笔记本 ODM + 渝欧铁路货运"},
      {"focus": "长安汽车、新能源车、先进制造"}
    ],
    "valuechain": "整机组装 + 封装（台资 ODM 负责笔记本，韩资负责存储后端）；汽车正向本土供应链转型；铁路物流优势显著。",
    "sourcing": {
      "buy": [
        "笔记本（Quanta/Inventec）",
        "新能源车（Changan/AVATR/Seres）",
        "DRAM/NAND 封装",
        "显示面板"
      ],
      "sell": [
        "笔记本供 OEM 品牌",
        "新能源车",
        "封装存储芯片"
      ]
    },
    "stats": [
      {"k": "笔记本", "v": "约占全球 30%（连续 11 年第 1）"},
      {"k": "新能源车 2024", "v": "95.3 万辆（+90.5%）"},
      {"k": "GDP 2024", "v": "¥3.22 万亿"}
    ],
    "note": "Quanta/Inventec/Foxconn（台）、SK hynix（韩）均为分支运营；HP/Dell 为品牌客户，非制造商。"
  },
  "Dongguan": {
    "tagline": "珠三角量产骨干——约 32 个专业镇；长安每分钟产出约 195 部手机，全市生产全球约 1/5 的手机；以模具速度与供应商密度取胜，而非品牌或芯片 IP。",
    "clusters": [
      {"seg": "智能手机 / 消费类 OEM-ODM", "what": "长安电子产值 ¥2,326 亿（2024）；自 1995 年起占全球手机约 1/5。"},
      {"seg": "PCB 及 PCBA", "what": "中国三大 PCB 中心之一（厚街/横沥/大朗）；紧密对接深圳设计公司。"},
      {"seg": "电池包", "what": "手机/TWS/电动工具电芯到电池包（电芯来自深圳/惠州）。"},
      {"seg": "精密冲压与模具", "what": "长安/厚街模具集群（约 ¥500 亿）；模具远销全球。"}
    ],
    "subdistricts": [
      {"focus": "智能手机 OEM/ODM + 模具——GDP >¥1,050 亿"},
      {"focus": "PCB 子集群（兼具家具产业）"},
      {"focus": "电池包组装，精密五金"}
    ],
    "valuechain": "典型 Tier-1/2 OEM——将深圳设计/零部件转化为成品组件；私营中小企业为主，利润率薄，正向智能制造转型。",
    "sourcing": {
      "buy": [
        "IC/模组（华强北/进口）",
        "裸 PCB",
        "电芯",
        "冲压件",
        "显示屏"
      ],
      "sell": [
        "组装手机、TWS、电动工具包、PCBA——供深圳品牌及出口"
      ]
    },
    "stats": [
      {"k": "GDP 2024", "v": "¥12,280 亿（+4.6%）"},
      {"k": "长安电子产值", "v": "¥2,326 亿"},
      {"k": "产出", "v": "约 195 部手机/分钟"}
    ],
    "note": "OPPO/vivo（BBK 系）以长安为核心；”全球手机 1/5”为数量级估算。"
  },
  "Foshan": {
    "tagline": "珠三角家电 + 工业材料腹地——顺德集聚美的（家电 + KUKA 机器人）和格兰仕，为全球最大白色家电集中生产地；佛山制造家居内部所需的一切。",
    "clusters": [
      {"seg": "家用电器 / 白色家电", "what": "顺德产值约 ¥3,700 亿；全球电饭煲 25%、微波炉 48%；Midea 2024 年营收 ¥4,090 亿。"},
      {"seg": "工业机器人", "what": "Midea-KUKA 顺德园——中国最大工业机器人基地（累计交付逾 80,000 台）。"},
      {"seg": "陶瓷砖", "what": "占全国约 54% / 全球约 25%；350 余家厂商，年产约 12 亿平方米。"},
      {"seg": "铝型材", "what": "南海——中国领先的建筑铝型材挤压中心。"}
    ],
    "subdistricts": [
      {"focus": "家电——Midea/格兰仕/KUKA"},
      {"focus": "陶瓷砖"},
      {"focus": "铝型材挤压，家具五金"}
    ],
    "valuechain": "中端至成品消费耐用品 + 建筑材料；高度私营（Midea/格兰仕）；Midea 已实现垂直整合（自制压缩机/电机/芯片）。",
    "sourcing": {
      "buy": [
        "钢材及压缩机零部件",
        "铜线",
        "铝锭",
        "稀土电机",
        "智能家电用 MCU/SoC（经深圳采购）"
      ],
      "sell": [
        "空调/洗衣机/电饭煲/微波炉",
        "工业机器人",
        "陶瓷砖",
        "铝型材"
      ]
    },
    "stats": [
      {"k": "Midea 2024", "v": "营收 ¥4,090 亿"},
      {"k": "陶瓷砖", "v": "占全国 54% / 全球 25%"},
      {"k": "KUKA", "v": "累计交付逾 80,000 台机器人"}
    ],
    "note": "KUKA 总部德国（顺德为制造基地）；海信总部青岛（在佛山设有工厂，非佛山总部）。"
  },
  "Ningde": {
    "tagline": "全球密度最高的单一城市电池生态系统——以 CATL 为核心的目的地型电池之都，上游材料、电芯生产与回收全链条本地集聚；产值 >¥3,000 亿。",
    "clusters": [
      {"seg": "电芯（动力 + 储能）", "what": "CATL 总部——连续 9 年全球新能源车电池第 1，2025 年全球份额 39.2%；出货量 661GWh。"},
      {"seg": "电池供应链", "what": "90 余家上下游企业；本地化材料比例 >60%（正极/负极/隔膜/电解液）。"},
      {"seg": "储能", "what": "CATL 储能 2025 年 Q3 出货 36GWh；Tener / Shenxing 电芯。"},
      {"seg": "电池回收", "what": "BRUNP（CATL）将退役电芯回收为前驱体材料。"}
    ],
    "subdistricts": [
      {"focus": "CATL 主园区 + 总部，超级工厂"},
      {"focus": "电池供应链及材料"}
    ],
    "valuechain": "几乎全部为民营（CATL，曾毓群控股）；电芯 + 材料制造；向全球 OEM 销售电芯；国企存在感极低。",
    "sourcing": {
      "buy": [
        "锂、钴、镍",
        "石墨负极",
        "PVDF 粘结剂",
        "电解液溶剂"
      ],
      "sell": [
        "新能源车动力电芯/电池包（NMC/LFP/麒麟）",
        "电网储能系统",
        "回收前驱体材料"
      ]
    },
    "stats": [
      {"k": "集群产值 2025", "v": "¥3,000 亿以上"},
      {"k": "CATL 2025", "v": "营收 ¥4,237 亿 / 净利润 ¥722 亿"},
      {"k": "市场份额", "v": "全球 39.2%，连续 9 年第 1"}
    ],
    "note": "CATL 另在溧阳/青岛/宜春等地设有工厂；”661GWh”为集团整体数据，非仅宁德产能。"
  },
  "Changzhou": {
    "tagline": "深圳以外全产业链最完整的新能源城市——CATL、SVOLT、CALB（电芯）、Li Auto（整车）与 Trina Solar（光伏）均在此制造。",
    "clusters": [
      {"seg": "电芯制造", "what": "三家并行——CATL 溧阳、SVOLT（金坛总部）、CALB（常州总部）；仅金坛一地即达 108.5GWh（约占全国 20%）。"},
      {"seg": "新能源车整车组装", "what": "Li Auto 主工厂（武进）；全市新能源车产量 67.8 万辆（2023）→ 80 万辆以上（2024）。"},
      {"seg": "太阳能光伏", "what": "Trina Solar 总部——全球前五组件厂商；2024 年营收 $112.7 亿；2024 年上半年出货 34GW。"},
      {"seg": "新能源车供应链零部件", "what": "深度 Tier-1/2——电解液、热管理、BMS、功率电子；新能源产值 ¥7,680 亿（2023）。"}
    ],
    "subdistricts": [
      {"focus": "SVOLT 总部——江苏最大电池基地"},
      {"focus": "CATL + CALB 电芯；电池材料"},
      {"focus": "Li Auto 新能源车整车组装"},
      {"focus": "Trina Solar 总部；光伏组件生产"}
    ],
    "valuechain": "国企/民营混合；中游电芯制造 + 整车组装；区域内采购材料，经长三角出口。",
    "sourcing": {
      "buy": [
        "LFP/NMC 正极",
        "石墨负极",
        "铜箔、铝壳",
        "硅片、EVA/背板"
      ],
      "sell": [
        "新能源车电芯/电池包",
        "新能源车 / 增程式车（Li Auto）",
        "光伏组件（销往 100 余国）",
        "储能系统"
      ]
    },
    "stats": [
      {"k": "新能源产值", "v": "¥7,680 亿（2023，目标 ¥1 万亿）"},
      {"k": "新能源车 2024", "v": "80 万辆以上"},
      {"k": "Trina Solar 2024", "v": "$112.7 亿"}
    ],
    "note": "Li Auto 总部北京（制造在常州）；CALB 2015 年迁自洛阳；CATL 总部宁德。"
  }
}
